asyncprocess/__init__.py
asyncprocess/async_process.py
asyncprocess/async_task.py
asyncprocess-0.0.5.dist-info/METADATA
asyncprocess-0.0.5.dist-info/WHEEL
asyncprocess-0.0.5.dist-info/top_level.txt
asyncprocess-0.0.5.dist-info/RECORD
