Metadata-Version: 2.1
Name: asyncprocess
Version: 0.0.5
Summary: Process managing async task
Home-page: https://github.com/Yakkuru/asyncprocess
Author: Marc-Antoine St-Pierre
Author-email: <yakinquiries@gmail.com>
License: UNKNOWN
Keywords: python,asyncio,async,task
Platform: UNKNOWN
Requires-Python: ~=3.7
